greenflow/__init__.py
greenflow/_common.py
greenflow/flow.py
greenflow/dataframe_flow/__init__.py
greenflow/dataframe_flow/_node.py
greenflow/dataframe_flow/_node_extension_mixin.py
greenflow/dataframe_flow/_node_flow.py
greenflow/dataframe_flow/_node_taskgraph_extension_mixin.py
greenflow/dataframe_flow/config_nodes_modules.py
greenflow/dataframe_flow/metaSpec.py
greenflow/dataframe_flow/node.py
greenflow/dataframe_flow/output_collector_node.py
greenflow/dataframe_flow/portsSpecSchema.py
greenflow/dataframe_flow/task.py
greenflow/dataframe_flow/taskGraph.py
greenflow/dataframe_flow/taskSpecSchema.py
greenflow/dataframe_flow/template_node_mixin.py
greenflow/dataframe_flow/util.py
greenflow/plugin_nodes/__init__.py
greenflow/plugin_nodes/util/__init__.py
greenflow/plugin_nodes/util/compositeNode.py
greenflow/plugin_nodes/util/contextCompositeNode.py
greenflow/plugin_nodes/util/data_obj.py
greenflow/plugin_nodes/util/json_util.py
greenflow-1.0.5.dist-info/LICENSE
greenflow-1.0.5.dist-info/METADATA
greenflow-1.0.5.dist-info/WHEEL
greenflow-1.0.5.dist-info/entry_points.txt
greenflow-1.0.5.dist-info/top_level.txt
greenflow-1.0.5.dist-info/RECORD
