Metadata-Version: 2.1
Name: greenflow
Version: 1.0.5
Summary: greenflow - RAPIDS Financial Services Algorithms
Home-page: https://github.com/NVIDIA/fsi-samples/tree/main/greenflow
Author: NVIDIA Corporation
License: Apache
Platform: UNKNOWN
Classifier: Development Status :: 4 - Beta
Classifier: Intended Audience :: Developers
Classifier: Intended Audience :: Science/Research
Classifier: Programming Language :: Python :: 3
Classifier: Operating System :: POSIX :: Linux
Requires-Dist: dask[distributed]
Requires-Dist: dask[dataframe]
Requires-Dist: configparser
Requires-Dist: cloudpickle
Requires-Dist: PyYaml
Requires-Dist: jsonpath-ng
Requires-Dist: ruamel.yaml
Requires-Dist: pandas
